[{"model": "order.element", "pk": 121, "fields": {"name": "mCommunityName", "display_seq_no": 10, "label": "Enter MCommunity Group Name:", "description": "", "help_text": "", "step": 67, "type": "McGroup", "attributes": "", "display_condition": "", "target": null}}, {"model": "order.element", "pk": 122, "fields": {"name": "nodeName", "display_seq_no": 20, "label": "Enter Node name to backup:", "description": "", "help_text": "", "step": 67, "type": "ST", "attributes": "", "display_condition": "", "target": null}}, {"model": "order.element", "pk": 123, "fields": {"name": "backUpTime", "display_seq_no": 30, "label": "Scheduled Backup Time:", "description": "", "help_text": "", "step": 67, "type": "ST", "attributes": "", "display_condition": "", "target": null}}, {"model": "order.element", "pk": 124, "fields": {"name": "preferredRetention", "display_seq_no": 40, "label": "Preferred Retention Values", "description": "<strong>Preferred Retention Values:</strong>", "help_text": "", "step": 67, "type": "HTML", "attributes": "", "display_condition": "", "target": null}}, {"model": "order.element", "pk": 130, "fields": {"name": "preferredOption1", "display_seq_no": 50, "label": "Version while the data exists", "description": "", "help_text": "", "step": 67, "type": "ST", "attributes": "", "display_condition": "", "target": null}}, {"model": "order.element", "pk": 131, "fields": {"name": "preferredOption2", "display_seq_no": 60, "label": "versions while the data deleted", "description": "", "help_text": "", "step": 67, "type": "ST", "attributes": "", "display_condition": "", "target": null}}, {"model": "order.element", "pk": 132, "fields": {"name": "preferredOption3", "display_seq_no": 70, "label": "days to retain extra versions", "description": "", "help_text": "", "step": 67, "type": "ST", "attributes": "", "display_condition": "", "target": null}}, {"model": "order.element", "pk": 133, "fields": {"name": "preferredOption4", "display_seq_no": 80, "label": "days to retain only version", "description": "", "help_text": "", "step": 67, "type": "ST", "attributes": "", "display_condition": "", "target": null}}]