[{"model": "order.element", "pk": 97, "fields": {"name": "shortcode", "display_seq_no": 10, "label": "Enter a Shortcode for costs to be billed to", "description": "", "help_text": "", "step": 60, "type": "ShortCode", "attributes": "", "display_condition": "", "target": "shortcode"}}, {"model": "order.element", "pk": 99, "fields": {"name": "billingAuthority", "display_seq_no": 30, "label": "Billing Authority", "description": "", "help_text": "", "step": 60, "type": "Checkbox", "attributes": "(('yes', 'I confirm I have approval from an individual with the authority to use the shortcode.'),)", "display_condition": "", "target": null}}, {"model": "order.element", "pk": 100, "fields": {"name": "serviceLvlAgreement", "display_seq_no": 60, "label": "Service Level Agreement", "description": "", "help_text": "", "step": 60, "type": "Checkbox", "attributes": "(('yes', 'I have read the Sensitive Data Guide, agree that my use of this service complies with those guidelines and accept the terns of the Service Level Agreement.'),)", "display_condition": "", "target": null}}, {"model": "order.element", "pk": 117, "fields": {"name": "totalCost", "display_seq_no": 4, "label": "Total Cost", "description": "<div class=\"alert alert-secondary col-3\">\r\n<strong>Your monthly charge:</strong>\r\n$<span id=\"totalCharge\">~</span>\r\n</div>", "help_text": "", "step": 60, "type": "HTML", "attributes": "", "display_condition": "", "target": null}}, {"model": "order.element", "pk": 121, "fields": {"name": "mCommunityName", "display_seq_no": 10, "label": "Enter MCommunity Group Name:", "description": "", "help_text": "", "step": 67, "type": "McGroup", "attributes": "", "display_condition": "", "target": null}}, {"model": "order.element", "pk": 122, "fields": {"name": "nodeNames", "display_seq_no": 20, "label": "Enter Node name and backup time:", "description": "", "help_text": "", "step": 67, "type": "ST", "attributes": "", "display_condition": "", "target": null}}, {"model": "order.element", "pk": 124, "fields": {"name": "preferredRetention", "display_seq_no": 40, "label": "Preferred Retention Values", "description": "<strong>Preferred Retention Values:</strong>", "help_text": "", "step": 67, "type": "HTML", "attributes": "", "display_condition": "", "target": null}}, {"model": "order.element", "pk": 130, "fields": {"name": "preferredOption1", "display_seq_no": 50, "label": "Number of Versions while data exists.", "description": "", "help_text": "", "step": 67, "type": "NU", "attributes": "30", "display_condition": "", "target": null}}, {"model": "order.element", "pk": 131, "fields": {"name": "preferredOption2", "display_seq_no": 60, "label": "Number of Versions after data is deleted.", "description": "", "help_text": "", "step": 67, "type": "NU", "attributes": "30", "display_condition": "", "target": null}}, {"model": "order.element", "pk": 132, "fields": {"name": "preferredOption3", "display_seq_no": 70, "label": "Days to retain extra Versions", "description": "", "help_text": "", "step": 67, "type": "NU", "attributes": "30", "display_condition": "", "target": null}}, {"model": "order.element", "pk": 133, "fields": {"name": "preferredOption4", "display_seq_no": 80, "label": "Days to retain only Version", "description": "", "help_text": "", "step": 67, "type": "NU", "attributes": "30", "display_condition": "", "target": null}}, {"model": "order.element", "pk": 145, "fields": {"name": "backupTime", "display_seq_no": 25, "label": "Backup Time", "description": "", "help_text": "", "step": 67, "type": "ST", "attributes": "['6:00 PM','7:00 PM','8:00 PM','9:00 PM','10:00 PM','11:00 PM','12:00 AM','1:00 AM','2:00 AM']", "display_condition": "", "target": null}}]